{
  "conservative_contact_pooling": false,
  "double_count_main_diagonal": false,
  "angles_on": true,
  "k_angle": 0,
  "cell_volumes": false,
  "compressibility_on": false,
  "kappa": 20,
  "parallel": false,
  "boundary_type": "sphere",
  "contact_bead_skipping": false,
  "binding_on": false,
  "track_contactmap": false,
  "visit_tracking": false,
  "dump_density": false,
  "update_contacts_distance": false,
  "boundary_attract_on": false,
  "boundary_chi": 0,
  "nbeads": 1024,
  "seed": 82353,
  "profiling_on": false,
  "print_trans": false,
  "print_acceptance_rates": true,
  "contact_resolution": 1,
  "constant_chi": 0,
  "constant_chi_on": false,

  "lmatrix_on": true,
  "smatrix_on": true,
  "dmatrix_on": true,

  "decay_length": 500,
  "nSweeps": 50000,
  "dump_frequency": 50000,
  "dump_stats_frequency": 100,
  "nEquilibSweeps": 1,

  "bonded_on": true,
  "nonbonded_on": true,
  "diagonal_on": true,
  "plaid_on": true,

  "displacement_on": false,
  "translation_on": true,
  "crankshaft_on": true,
  "pivot_on": true,
  "rotate_on": false,
  "gridmove_on": true,

  "density_cap_on": true,
  "phi_solvent_max": 0.5,
  "phi_chromatin": 0.06,

  "bond_type": "gaussian",
  "bond_length": 30,
  "beadvol": 520,
  "grid_size": 28.7,

  "diag_start": 0,
  "dense_diagonal_on": true,
  "diag_pseudobeads_on": true,
  "dense_diagonal_cutoff": 0.0625,
  "dense_diagonal_loading": 0.5,
  "diagonal_linear": true,
  "diag_chis": [0, 0, 0, 0, 0, 0, 0, 0, 0, 0, 0, 0, 0, 0, 0, 0, 0, 0, 0, 0, 0, 0, 0, 0, 0, 0, 0, 0, 0, 0, 0, 0, 0, 0, 0, 0, 0, 0, 0, 0, 0, 0, 0, 0, 0, 0, 0, 0, 0, 0, 0, 0, 0, 0, 0, 0, 0, 0, 0, 0, 0, 0, 0, 0 ],

  "load_configuration": false,
  "load_configuration_filename": "equilibrated.xyz",

  "load_bead_types": true,
  "load_chipseq": true,
  "nspecies": 5,
  "bead_type_files": ["pcf1.txt", "pcf2.txt", "pcf3.txt", "pcf4.txt", "pcf5.txt"],
  "chis": [
    [0.0, 0.0, 0.0, 0.0, 0.0],
    [0.0, 0.0, 0.0, 0.0, 0.0],
    [0.0, 0.0, 0.0, 0.0, 0.0],
    [0.0, 0.0, 0.0, 0.0, 0.0],
    [0.0, 0.0, 0.0, 0.0, 0.0]
  ]
}
